spacetransformer/__init__.py
spacetransformer/core/__init__.py
spacetransformer/core/_version.py
spacetransformer/core/exceptions.py
spacetransformer/core/pointset_warpers.py
spacetransformer/core/relation_check.py
spacetransformer/core/space.py
spacetransformer/core/transform.py
spacetransformer/core/validation.py
spacetransformer_core-0.2.6.dist-info/METADATA
spacetransformer_core-0.2.6.dist-info/WHEEL
spacetransformer_core-0.2.6.dist-info/top_level.txt
spacetransformer_core-0.2.6.dist-info/RECORD
