Metadata-Version: 2.4
Name: spacetransformer-core
Version: 0.2.6
Summary: Pure numpy core implementation of Space Transformer for geometric computations.
Author-email: Your Name <you@example.com>
License: MIT
Keywords: medical-imaging,geometry,transform,numpy
Classifier: Development Status :: 3 - Alpha
Classifier: Intended Audience :: Developers
Classifier: License :: OSI Approved :: MIT License
Classifier: Programming Language :: Python :: 3
Classifier: Programming Language :: Python :: 3.8
Classifier: Programming Language :: Python :: 3.9
Classifier: Programming Language :: Python :: 3.10
Classifier: Programming Language :: Python :: 3.11
Classifier: Programming Language :: Python :: 3.12
Requires-Python: >=3.8
Requires-Dist: numpy>=1.20
Provides-Extra: test
Requires-Dist: pytest; extra == "test"
Provides-Extra: dev
Requires-Dist: pytest; extra == "dev"
